sound_sleep/__init__.py
sound_sleep/aggregators.py
sound_sleep/sleep_features.py
sound_sleep/io/__init__.py
sound_sleep/io/exports.py
sound_sleep/io/loader.py
sound_sleep-0.6.dist-info/METADATA
sound_sleep-0.6.dist-info/WHEEL
sound_sleep-0.6.dist-info/top_level.txt
sound_sleep-0.6.dist-info/RECORD
