Metadata-Version: 2.1
Name: sound-sleep
Version: 0.6
Summary: SoundSleep is a Python package for extracting comprehensive sleep features from wearable or sleep stage-labeled data.
Home-page: UNKNOWN
Author: Trym Drag-Erlandsen, Alireza Delfarah, and Chuyi Zhang
License: MIT
Platform: UNKNOWN
Requires-Python: >=3.7
Requires-Dist: pandas
Requires-Dist: numpy
